decart/__init__.py
decart/_user_agent.py
decart/_version.py
decart/client.py
decart/errors.py
decart/models.py
decart/types.py
decart/lipsync/__init__.py
decart/lipsync/client.py
decart/lipsync/messages.py
decart/process/__init__.py
decart/process/request.py
decart/queue/__init__.py
decart/queue/client.py
decart/queue/request.py
decart/queue/types.py
decart/realtime/__init__.py
decart/realtime/client.py
decart/realtime/messages.py
decart/realtime/types.py
decart/realtime/webrtc_connection.py
decart/realtime/webrtc_manager.py
decart/tokens/__init__.py
decart/tokens/client.py
decart/tokens/types.py
decart/py.typed
decart-0.0.17.dist-info/METADATA
decart-0.0.17.dist-info/WHEEL
decart-0.0.17.dist-info/entry_points.txt
decart-0.0.17.dist-info/licenses/LICENSE
decart-0.0.17.dist-info/RECORD
