Metadata-Version: 2.1
Name: decart
Version: 0.0.17
Summary: Decart's Python SDK
Project-URL: Homepage, https://github.com/decartai/decart-python
Project-URL: Documentation, https://docs.platform.decart.ai/sdks/python
Project-URL: Repository, https://github.com/decartai/decart-python
Project-URL: Issues, https://github.com/decartai/decart-python/issues
Author-email: Adir Amsalem <adir@decart.ai>
License: MIT
Keywords: ai,decart,generation,image,transformation,video
Classifier: Development Status :: 3 - Alpha
Classifier: Intended Audience :: Developers
Classifier: License :: OSI Approved :: MIT License
Classifier: Programming Language :: Python :: 3
Classifier: Programming Language :: Python :: 3.10
Classifier: Programming Language :: Python :: 3.11
Classifier: Programming Language :: Python :: 3.12
Classifier: Programming Language :: Python :: 3.13
Classifier: Programming Language :: Python :: 3.14
Requires-Python: >=3.10
Requires-Dist: aiofiles>=23.0.0
Requires-Dist: aiohttp>=3.9.0
Requires-Dist: numpy>=2.0.2
Requires-Dist: opencv-python>=4.11.0.86
Requires-Dist: pydantic>=2.0.0
Requires-Dist: websockets>=15.0.1
Provides-Extra: dev
Requires-Dist: black>=23.0.0; extra == 'dev'
Requires-Dist: mypy>=1.0.0; extra == 'dev'
Requires-Dist: pytest-asyncio>=0.21.0; extra == 'dev'
Requires-Dist: pytest-cov>=4.0.0; extra == 'dev'
Requires-Dist: pytest>=7.0.0; extra == 'dev'
Requires-Dist: ruff>=0.1.0; extra == 'dev'
Provides-Extra: realtime
Requires-Dist: aiortc>=1.9.0; extra == 'realtime'
Requires-Dist: av>=12.0.0; extra == 'realtime'
Requires-Dist: tenacity>=8.0.0; extra == 'realtime'
